{
    "key": "seamark:restricted_area:restriction",
    "type": "semiCombo",
    "label": "Restriction",
    "strings": {
        "options": {
            "no_anchoring": "Anchoring prohibited",
            "restricted_anchoring": "Anchoring restricted",
            "no_fishing": "Fishing prohibited",
            "restricted_fishing": "Fishing restricted",
            "no_trawling": "Trawling prohibited",
            "restricted_trawling": "Trawling restricted",
            "no_entry": "Entry prohibited",
            "restricted_entry": "Entry restricted",
            "no_dredging": "Dredging prohibited",
            "restricted_dredging": "Dredging restricted",
            "no_diving": "Diving prohibited",
            "restricted_diving": "Diving restricted",
            "no_wake": "No wake",
            "to_be_avoided": "Area to be avoided",
            "no_construction": "Construction prohibited",
            "no_discharging": "Discharging prohibited",
            "restricted_discharging": "Discharging restricted",
            "no_exploration_development": "Industrial or mineral exploration/development prohibited",
            "restricted_exploration_development": "Industrial or mineral exploration/development restricted",
            "no_drilling": "Drilling prohibited",
            "restricted_drilling": "Drilling restricted",
            "no_historical_artifacts_removal": "Removal of historical artifacts prohibited",
            "no_lightering": "Cargo transhipment (lightering) prohibited",
            "no_dragging": "Dragging prohibited",
            "no_stopping": "Stopping prohibited",
            "no_landing": "Landing prohibited",
            "restricted_speed": "Speed restricted",
            "no_overtaking": "Overtaking prohibited",
            "no_convoy_overtaking": "Overtaking of convoys by convoys prohibited",
            "no_passing_overtaking": "Passing or overtaking prohibited",
            "no_berthing": "Berthing prohibited",
            "restricted_berthing": "Berthing restricted",
            "no_making_fast": "Making fast prohibited",
            "restricted_making_fast": "Making fast restricted",
            "no_turning": "Turning prohibited",
            "restricted_fairway_depth": "Restricted fairway depth"
        }
    }
}
